{
  "2026-02-11": [],
  "2026-02-12": [],
  "2026-02-13": [],
  "2026-02-14": [],
  "2026-02-15": [],
  "2026-02-16": [],
  "2026-02-17": [],
  "2026-02-18": [
    "Geen premières vandaag",
    "Geen premières vandaag",
    {
      "tijdstip": "2026-02-18T14:44:35.099Z",
      "aantal": 0,
      "premieres": []
    },
    {
      "tijdstip": "2026-02-18T14:56:39.672Z",
      "aantal": 0,
      "premieres": []
    },
    {
      "tijdstip": "2026-02-18T15:02:32.067Z",
      "aantal": 0,
      "premieres": []
    }
  ],
  "2026-02-19": [
    {
      "tijdstip": "2026-02-19T07:55:38.196Z",
      "aantal": 0,
      "premieres": []
    }
  ],
  "2026-02-20": [
    {
      "tijdstip": "2026-02-20T07:38:53.602Z",
      "aantal": 0,
      "premieres": []
    }
  ],
  "2026-02-21": [
    {
      "tijdstip": "2026-02-21T07:08:59.968Z",
      "aantal": 0,
      "premieres": []
    }
  ],
  "2026-02-22": [
    {
      "tijdstip": "2026-02-22T07:25:21.712Z",
      "aantal": 0,
      "premieres": []
    }
  ],
  "2026-02-23": [
    {
      "tijdstip": "2026-02-23T08:01:03.965Z",
      "aantal": 0,
      "premieres": []
    }
  ],
  "2026-02-24": [
    {
      "tijdstip": "2026-02-24T07:57:32.183Z",
      "aantal": 0,
      "premieres": []
    }
  ],
  "2026-02-25": [
    {
      "tijdstip": "2026-02-25T07:59:34.902Z",
      "aantal": 0,
      "premieres": []
    }
  ],
  "2026-02-26": [
    {
      "tijdstip": "2026-02-26T07:57:05.305Z",
      "aantal": 0,
      "premieres": []
    }
  ],
  "2026-02-27": [
    {
      "tijdstip": "2026-02-27T07:36:27.608Z",
      "aantal": 0,
      "premieres": []
    }
  ],
  "2026-02-28": [
    {
      "tijdstip": "2026-02-28T05:59:13.461Z",
      "aantal": 0,
      "premieres": []
    }
  ]
}